brucezilany-0.0.1.dist-info/top_level.txt
brucezilany-0.0.1.dist-info/RECORD
brucezilany-0.0.1.dist-info/METADATA
brucezilany-0.0.1.dist-info/WHEEL
brucezilany/brucezilanycpp.cpython-39-x86_64-linux-gnu.so
brucezilany/__init__.py
brucezilany/plot.py
