Metadata-Version: 2.4
Name: brucezilany
Version: 0.0.1
Summary: Python/C++ interface to the Bruce-Zilany-Carney auditory nerve model
Home-page: https://github.com/jacobdenobel/brucezilany
Author: Jacob de Nobel
Author-email: jacobdenobel@gmail.com
License: BSD-3-Clause OR Other (if applicable)
Project-URL: Original Model, https://www.ece.mcmaster.ca/~ibruce/zbcANmodel/zbcANmodel.htm
Project-URL: Source, https://github.com/jacobdenobel/brucezilany
Classifier: Programming Language :: Python :: 3
Classifier: Programming Language :: C++
Classifier: License :: OSI Approved :: BSD License
Classifier: Operating System :: OS Independent
Classifier: Topic :: Scientific/Engineering :: Bio-Informatics
Classifier: Intended Audience :: Science/Research
Requires-Python: >=3.7
Requires-Dist: numpy
Requires-Dist: scipy
Requires-Dist: matplotlib
Requires-Dist: librosa
Dynamic: author
Dynamic: author-email
Dynamic: classifier
Dynamic: description
Dynamic: description-content-type
Dynamic: home-page
Dynamic: license
Dynamic: project-url
Dynamic: requires-dist
Dynamic: requires-python
Dynamic: summary
